[
    {
        "colo": "Default",
        "ip": "2606:4700:85dd:54d3:4652:a83b:c9a1:f066",
        "latency": 149,
        "line": "CM",
        "loss": 0,
        "node": "CBUS",
        "speed": 549,
        "time": "2024-10-16 02:32:13"
    },
    {
        "colo": "Default",
        "ip": "2606:4700:85dd:b06b:be30:6368:fc45:b67a",
        "latency": 164,
        "line": "CM",
        "loss": 0,
        "node": "CBUS",
        "speed": 505,
        "time": "2024-10-16 02:32:13"
    },
    {
        "colo": "Default",
        "ip": "2606:4700:85dd:9ccd:1e6d:b6dd:41ca:b2f2",
        "latency": 164,
        "line": "CM",
        "loss": 0,
        "node": "CBUS",
        "speed": 490,
        "time": "2024-10-16 02:32:13"
    },
    {
        "colo": "Default",
        "ip": "2606:4700:9aee:2bff:e886:6ff6:4bb9:8bc6",
        "latency": 161,
        "line": "CM",
        "loss": 0,
        "node": "CBUS",
        "speed": 450,
        "time": "2024-10-16 02:32:13"
    },
    {
        "colo": "Default",
        "ip": "2606:4700:9aee:702d:9b8d:de8f:8b1b:7a1e",
        "latency": 151,
        "line": "CM",
        "loss": 0,
        "node": "CBUS",
        "speed": 340,
        "time": "2024-10-16 02:32:13"
    },
    {
        "colo": "Default",
        "ip": "2606:4700:9ae5:5a77:5efa:a40d:a9ad:f91b",
        "latency": 24,
        "line": "CT",
        "loss": 0,
        "node": "WEBH",
        "speed": 309,
        "time": "2024-10-16 00:15:40"
    },
    {
        "colo": "Default",
        "ip": "2606:4700:8ddb:9a82:af76:1b20:eba:6da",
        "latency": 20,
        "line": "CT",
        "loss": 0,
        "node": "WEBH",
        "speed": 308,
        "time": "2024-10-16 00:15:37"
    },
    {
        "colo": "Default",
        "ip": "2606:4700:8ddb:e37d:733c:b36a:b88:a7d8",
        "latency": 20,
        "line": "CT",
        "loss": 0,
        "node": "WEBH",
        "speed": 307,
        "time": "2024-10-16 00:15:39"
    },
    {
        "colo": "Default",
        "ip": "2606:4700:9ae5:691b:cf86:658a:1dd2:8e1d",
        "latency": 19,
        "line": "CT",
        "loss": 0,
        "node": "WEBH",
        "speed": 307,
        "time": "2024-10-16 00:15:38"
    },
    {
        "colo": "Default",
        "ip": "2606:4700:9ae5:11e2:da89:f159:5e49:ed99",
        "latency": 20,
        "line": "CT",
        "loss": 0,
        "node": "WEBH",
        "speed": 307,
        "time": "2024-10-16 00:15:37"
    },
    {
        "colo": "Default",
        "ip": "2606:4700:85dd:54d3:4652:a83b:c9a1:f066",
        "latency": 149,
        "line": "CU",
        "loss": 0,
        "node": "CBUS",
        "speed": 549,
        "time": "2024-10-16 02:32:13"
    },
    {
        "colo": "Default",
        "ip": "2606:4700:85dd:b06b:be30:6368:fc45:b67a",
        "latency": 164,
        "line": "CU",
        "loss": 0,
        "node": "CBUS",
        "speed": 505,
        "time": "2024-10-16 02:32:13"
    },
    {
        "colo": "Default",
        "ip": "2606:4700:85dd:9ccd:1e6d:b6dd:41ca:b2f2",
        "latency": 164,
        "line": "CU",
        "loss": 0,
        "node": "CBUS",
        "speed": 490,
        "time": "2024-10-16 02:32:13"
    },
    {
        "colo": "Default",
        "ip": "2606:4700:9aee:2bff:e886:6ff6:4bb9:8bc6",
        "latency": 161,
        "line": "CU",
        "loss": 0,
        "node": "CBUS",
        "speed": 450,
        "time": "2024-10-16 02:32:13"
    },
    {
        "colo": "Default",
        "ip": "2606:4700:9aee:702d:9b8d:de8f:8b1b:7a1e",
        "latency": 151,
        "line": "CU",
        "loss": 0,
        "node": "CBUS",
        "speed": 340,
        "time": "2024-10-16 02:32:13"
    }
]