[
    {
        "colo": "Default",
        "ip": "2606:4700:9764:918a:1fa7:23d:b6ff:1966",
        "latency": 149,
        "line": "CM",
        "loss": 0,
        "node": "CBUS",
        "speed": 579,
        "time": "2024-10-29 11:54:16"
    },
    {
        "colo": "Default",
        "ip": "2606:4700:101:d194:a605:350b:111f:956a",
        "latency": 11,
        "line": "CM",
        "loss": 0,
        "node": "CBUS",
        "speed": 517,
        "time": "2024-10-29 11:54:15"
    },
    {
        "colo": "Default",
        "ip": "2606:4700:101:ee57:788c:c851:6af0:b96a",
        "latency": 11,
        "line": "CM",
        "loss": 0,
        "node": "CBUS",
        "speed": 517,
        "time": "2024-10-29 11:54:15"
    },
    {
        "colo": "Default",
        "ip": "2606:4700:9764:8415:ca7e:8f3:8ce6:e5f",
        "latency": 147,
        "line": "CM",
        "loss": 0,
        "node": "CBUS",
        "speed": 487,
        "time": "2024-10-29 11:54:16"
    },
    {
        "colo": "Default",
        "ip": "2606:4700:9764:6698:ccee:8e0b:b4b9:af70",
        "latency": 149,
        "line": "CM",
        "loss": 0,
        "node": "CBUS",
        "speed": 429,
        "time": "2024-10-29 11:54:16"
    },
    {
        "colo": "Default",
        "ip": "2606:4700:9a9d:6d8d:4723:4536:bd22:4bd4",
        "latency": 25,
        "line": "CT",
        "loss": 0,
        "node": "WEBH",
        "speed": 309,
        "time": "2024-10-29 11:45:29"
    },
    {
        "colo": "Default",
        "ip": "2606:4700:9a9d:5c4a:80b1:3e15:495:5296",
        "latency": 25,
        "line": "CT",
        "loss": 0,
        "node": "WEBH",
        "speed": 308,
        "time": "2024-10-29 11:45:31"
    },
    {
        "colo": "Default",
        "ip": "2606:4700:9a9d:db70:42a:cd31:36ae:5c53",
        "latency": 19,
        "line": "CT",
        "loss": 0,
        "node": "WEBH",
        "speed": 308,
        "time": "2024-10-29 11:45:30"
    },
    {
        "colo": "Default",
        "ip": "2606:4700:99e4:16ab:b495:1733:ae35:598b",
        "latency": 20,
        "line": "CT",
        "loss": 0,
        "node": "WEBH",
        "speed": 308,
        "time": "2024-10-29 11:45:29"
    },
    {
        "colo": "Default",
        "ip": "2606:4700:99e4:6a06:5826:8a56:845c:2b4c",
        "latency": 24,
        "line": "CT",
        "loss": 0,
        "node": "WEBH",
        "speed": 307,
        "time": "2024-10-29 11:45:31"
    },
    {
        "colo": "Default",
        "ip": "2606:4700:9764:918a:1fa7:23d:b6ff:1966",
        "latency": 149,
        "line": "CU",
        "loss": 0,
        "node": "CBUS",
        "speed": 579,
        "time": "2024-10-29 11:54:16"
    },
    {
        "colo": "Default",
        "ip": "2606:4700:101:d194:a605:350b:111f:956a",
        "latency": 11,
        "line": "CU",
        "loss": 0,
        "node": "CBUS",
        "speed": 517,
        "time": "2024-10-29 11:54:15"
    },
    {
        "colo": "Default",
        "ip": "2606:4700:101:ee57:788c:c851:6af0:b96a",
        "latency": 11,
        "line": "CU",
        "loss": 0,
        "node": "CBUS",
        "speed": 517,
        "time": "2024-10-29 11:54:15"
    },
    {
        "colo": "Default",
        "ip": "2606:4700:9764:8415:ca7e:8f3:8ce6:e5f",
        "latency": 147,
        "line": "CU",
        "loss": 0,
        "node": "CBUS",
        "speed": 487,
        "time": "2024-10-29 11:54:16"
    },
    {
        "colo": "Default",
        "ip": "2606:4700:9764:6698:ccee:8e0b:b4b9:af70",
        "latency": 149,
        "line": "CU",
        "loss": 0,
        "node": "CBUS",
        "speed": 429,
        "time": "2024-10-29 11:54:16"
    }
]