[
    {
        "colo": "Default",
        "ip": "2606:4700:8ca9:f19c:6002:25:45b5:d47f",
        "latency": 162,
        "line": "CM",
        "loss": 0,
        "node": "CBUS",
        "speed": 563,
        "time": "2024-10-15 17:52:10"
    },
    {
        "colo": "Default",
        "ip": "2606:4700:8ca9:6171:c3c3:19c2:e83:81b6",
        "latency": 149,
        "line": "CM",
        "loss": 0,
        "node": "CBUS",
        "speed": 488,
        "time": "2024-10-15 17:52:10"
    },
    {
        "colo": "Default",
        "ip": "2606:4700:8ca9:df9:905c:fbb:84e3:be33",
        "latency": 164,
        "line": "CM",
        "loss": 0,
        "node": "CBUS",
        "speed": 461,
        "time": "2024-10-15 17:52:10"
    },
    {
        "colo": "Default",
        "ip": "2606:4700:8ca9:c3ba:a9bc:5f43:c8f:687d",
        "latency": 156,
        "line": "CM",
        "loss": 0,
        "node": "CBUS",
        "speed": 451,
        "time": "2024-10-15 17:52:10"
    },
    {
        "colo": "Default",
        "ip": "2606:4700:8ca9:d226:a6f4:f4cd:eeba:7fdd",
        "latency": 161,
        "line": "CM",
        "loss": 0,
        "node": "CBUS",
        "speed": 419,
        "time": "2024-10-15 17:52:10"
    },
    {
        "colo": "Default",
        "ip": "2606:4700:9ae7:c2fc:83b6:a56e:780f:6f35",
        "latency": 25,
        "line": "CT",
        "loss": 0,
        "node": "WEBH",
        "speed": 310,
        "time": "2024-10-15 17:55:40"
    },
    {
        "colo": "Default",
        "ip": "2606:4700:9ae7:5b37:85a2:4a82:b765:f5d5",
        "latency": 20,
        "line": "CT",
        "loss": 0,
        "node": "WEBH",
        "speed": 309,
        "time": "2024-10-15 17:55:38"
    },
    {
        "colo": "Default",
        "ip": "2606:4700:9ae7:7680:e63:3952:32a1:fffb",
        "latency": 25,
        "line": "CT",
        "loss": 0,
        "node": "WEBH",
        "speed": 309,
        "time": "2024-10-15 17:55:37"
    },
    {
        "colo": "Default",
        "ip": "2606:4700:9aea:7489:b023:f721:c02:bc26",
        "latency": 20,
        "line": "CT",
        "loss": 0,
        "node": "WEBH",
        "speed": 308,
        "time": "2024-10-15 17:55:39"
    },
    {
        "colo": "Default",
        "ip": "2606:4700:9ae7:1fdf:4bb8:35e8:2a61:5920",
        "latency": 26,
        "line": "CT",
        "loss": 0,
        "node": "WEBH",
        "speed": 307,
        "time": "2024-10-15 17:55:39"
    },
    {
        "colo": "Default",
        "ip": "2606:4700:8ca9:f19c:6002:25:45b5:d47f",
        "latency": 162,
        "line": "CU",
        "loss": 0,
        "node": "CBUS",
        "speed": 563,
        "time": "2024-10-15 17:52:10"
    },
    {
        "colo": "Default",
        "ip": "2606:4700:8ca9:6171:c3c3:19c2:e83:81b6",
        "latency": 149,
        "line": "CU",
        "loss": 0,
        "node": "CBUS",
        "speed": 488,
        "time": "2024-10-15 17:52:10"
    },
    {
        "colo": "Default",
        "ip": "2606:4700:8ca9:df9:905c:fbb:84e3:be33",
        "latency": 164,
        "line": "CU",
        "loss": 0,
        "node": "CBUS",
        "speed": 461,
        "time": "2024-10-15 17:52:10"
    },
    {
        "colo": "Default",
        "ip": "2606:4700:8ca9:c3ba:a9bc:5f43:c8f:687d",
        "latency": 156,
        "line": "CU",
        "loss": 0,
        "node": "CBUS",
        "speed": 451,
        "time": "2024-10-15 17:52:10"
    },
    {
        "colo": "Default",
        "ip": "2606:4700:8ca9:d226:a6f4:f4cd:eeba:7fdd",
        "latency": 161,
        "line": "CU",
        "loss": 0,
        "node": "CBUS",
        "speed": 419,
        "time": "2024-10-15 17:52:10"
    }
]