[
    {
        "colo": "Default",
        "ip": "2606:4700:13b:476d:7183:f07d:a9da:99d2",
        "latency": 1,
        "line": "CM",
        "loss": 0,
        "node": "WW_HK",
        "speed": 308,
        "time": "2024-11-06 21:56:33"
    },
    {
        "colo": "Default",
        "ip": "2606:4700:9a69:42c5:df30:e2e2:6a63:43b2",
        "latency": 2,
        "line": "CM",
        "loss": 0,
        "node": "WW_HK",
        "speed": 307,
        "time": "2024-11-06 21:56:32"
    },
    {
        "colo": "Default",
        "ip": "2606:4700:9a69:d188:9596:5cce:73ab:808f",
        "latency": 6,
        "line": "CM",
        "loss": 0,
        "node": "WW_HK",
        "speed": 307,
        "time": "2024-11-06 21:56:32"
    },
    {
        "colo": "Default",
        "ip": "2606:4700:9a69:fcad:243f:c15d:898c:b7e9",
        "latency": 1,
        "line": "CM",
        "loss": 0,
        "node": "WW_HK",
        "speed": 307,
        "time": "2024-11-06 21:56:31"
    },
    {
        "colo": "Default",
        "ip": "2606:4700:9a69:54bc:1b64:37c0:8e0f:6426",
        "latency": 2,
        "line": "CM",
        "loss": 0,
        "node": "WW_HK",
        "speed": 307,
        "time": "2024-11-06 21:56:30"
    },
    {
        "colo": "Default",
        "ip": "2606:4700:9c6c:91ee:efc5:9388:d5fc:2e49",
        "latency": 25,
        "line": "CT",
        "loss": 0,
        "node": "WEBH",
        "speed": 309,
        "time": "2024-11-06 21:55:24"
    },
    {
        "colo": "Default",
        "ip": "2606:4700:9c61:850f:3532:8cbb:9aff:4d45",
        "latency": 25,
        "line": "CT",
        "loss": 0,
        "node": "WEBH",
        "speed": 308,
        "time": "2024-11-06 21:55:26"
    },
    {
        "colo": "Default",
        "ip": "2606:4700:9c61:6db0:390e:623a:81b:b884",
        "latency": 20,
        "line": "CT",
        "loss": 0,
        "node": "WEBH",
        "speed": 308,
        "time": "2024-11-06 21:55:25"
    },
    {
        "colo": "Default",
        "ip": "2606:4700:9c61:ccb:5c83:683a:5005:910f",
        "latency": 24,
        "line": "CT",
        "loss": 0,
        "node": "WEBH",
        "speed": 308,
        "time": "2024-11-06 21:55:25"
    },
    {
        "colo": "Default",
        "ip": "2606:4700:9c61:b81e:9483:ef84:4272:4275",
        "latency": 20,
        "line": "CT",
        "loss": 0,
        "node": "WEBH",
        "speed": 308,
        "time": "2024-11-06 21:55:23"
    },
    {
        "colo": "Default",
        "ip": "2606:4700:13b:476d:7183:f07d:a9da:99d2",
        "latency": 1,
        "line": "CU",
        "loss": 0,
        "node": "WW_HK",
        "speed": 308,
        "time": "2024-11-06 21:56:33"
    },
    {
        "colo": "Default",
        "ip": "2606:4700:9a69:42c5:df30:e2e2:6a63:43b2",
        "latency": 2,
        "line": "CU",
        "loss": 0,
        "node": "WW_HK",
        "speed": 307,
        "time": "2024-11-06 21:56:32"
    },
    {
        "colo": "Default",
        "ip": "2606:4700:9a69:d188:9596:5cce:73ab:808f",
        "latency": 6,
        "line": "CU",
        "loss": 0,
        "node": "WW_HK",
        "speed": 307,
        "time": "2024-11-06 21:56:32"
    },
    {
        "colo": "Default",
        "ip": "2606:4700:9a69:fcad:243f:c15d:898c:b7e9",
        "latency": 1,
        "line": "CU",
        "loss": 0,
        "node": "WW_HK",
        "speed": 307,
        "time": "2024-11-06 21:56:31"
    },
    {
        "colo": "Default",
        "ip": "2606:4700:9a69:54bc:1b64:37c0:8e0f:6426",
        "latency": 2,
        "line": "CU",
        "loss": 0,
        "node": "WW_HK",
        "speed": 307,
        "time": "2024-11-06 21:56:30"
    }
]