[
    {
        "colo": "Default",
        "ip": "2606:4700:8398:3d2d:8779:a718:e222:ffa5",
        "latency": 151,
        "line": "CM",
        "loss": 0,
        "node": "CBUS",
        "speed": 815,
        "time": "2024-11-13 09:06:33"
    },
    {
        "colo": "Default",
        "ip": "2606:4700:8398:1773:bcf:bb72:4ae2:75be",
        "latency": 155,
        "line": "CM",
        "loss": 0,
        "node": "CBUS",
        "speed": 504,
        "time": "2024-11-13 09:06:33"
    },
    {
        "colo": "Default",
        "ip": "2606:4700:8398:f0fa:ba7d:e07a:8139:f5b",
        "latency": 149,
        "line": "CM",
        "loss": 0,
        "node": "CBUS",
        "speed": 493,
        "time": "2024-11-13 09:06:33"
    },
    {
        "colo": "Default",
        "ip": "2606:4700:90c4:9b7b:633f:6da4:5770:71f1",
        "latency": 155,
        "line": "CM",
        "loss": 0,
        "node": "CBUS",
        "speed": 460,
        "time": "2024-11-13 09:06:33"
    },
    {
        "colo": "Default",
        "ip": "2606:4700:8398:562e:cd95:9b23:447f:2a39",
        "latency": 159,
        "line": "CM",
        "loss": 0,
        "node": "CBUS",
        "speed": 440,
        "time": "2024-11-13 09:06:33"
    },
    {
        "colo": "Default",
        "ip": "2606:4700:8de9:c1a0:3dbf:729b:8c92:4809",
        "latency": 24,
        "line": "CT",
        "loss": 0,
        "node": "WEBH",
        "speed": 309,
        "time": "2024-11-13 08:45:19"
    },
    {
        "colo": "Default",
        "ip": "2606:4700:8de9:ed83:6e7a:d7c0:e2e2:aeb8",
        "latency": 25,
        "line": "CT",
        "loss": 0,
        "node": "WEBH",
        "speed": 308,
        "time": "2024-11-13 08:45:20"
    },
    {
        "colo": "Default",
        "ip": "2606:4700:8de3:bec7:ff7d:10ea:70e:7916",
        "latency": 19,
        "line": "CT",
        "loss": 0,
        "node": "WEBH",
        "speed": 308,
        "time": "2024-11-13 08:45:20"
    },
    {
        "colo": "Default",
        "ip": "2606:4700:8de3:bd3:5e9d:19e5:90e0:56ae",
        "latency": 24,
        "line": "CT",
        "loss": 0,
        "node": "WEBH",
        "speed": 308,
        "time": "2024-11-13 08:45:22"
    },
    {
        "colo": "Default",
        "ip": "2606:4700:8de9:a162:47b:b2d4:7464:8a28",
        "latency": 20,
        "line": "CT",
        "loss": 0,
        "node": "WEBH",
        "speed": 307,
        "time": "2024-11-13 08:45:21"
    },
    {
        "colo": "Default",
        "ip": "2606:4700:8398:3d2d:8779:a718:e222:ffa5",
        "latency": 151,
        "line": "CU",
        "loss": 0,
        "node": "CBUS",
        "speed": 815,
        "time": "2024-11-13 09:06:33"
    },
    {
        "colo": "Default",
        "ip": "2606:4700:8398:1773:bcf:bb72:4ae2:75be",
        "latency": 155,
        "line": "CU",
        "loss": 0,
        "node": "CBUS",
        "speed": 504,
        "time": "2024-11-13 09:06:33"
    },
    {
        "colo": "Default",
        "ip": "2606:4700:8398:f0fa:ba7d:e07a:8139:f5b",
        "latency": 149,
        "line": "CU",
        "loss": 0,
        "node": "CBUS",
        "speed": 493,
        "time": "2024-11-13 09:06:33"
    },
    {
        "colo": "Default",
        "ip": "2606:4700:90c4:9b7b:633f:6da4:5770:71f1",
        "latency": 155,
        "line": "CU",
        "loss": 0,
        "node": "CBUS",
        "speed": 460,
        "time": "2024-11-13 09:06:33"
    },
    {
        "colo": "Default",
        "ip": "2606:4700:8398:562e:cd95:9b23:447f:2a39",
        "latency": 159,
        "line": "CU",
        "loss": 0,
        "node": "CBUS",
        "speed": 440,
        "time": "2024-11-13 09:06:33"
    }
]