[
    {
        "colo": "Default",
        "ip": "2606:4700:3034:9c93:8606:f199:8992:3834",
        "latency": 11,
        "line": "CM",
        "loss": 0,
        "node": "CBUS",
        "speed": 538,
        "time": "2024-11-15 04:26:48"
    },
    {
        "colo": "Default",
        "ip": "2606:4700:3034:4fa9:2a43:355c:fadb:278d",
        "latency": 11,
        "line": "CM",
        "loss": 0,
        "node": "CBUS",
        "speed": 527,
        "time": "2024-11-15 04:26:48"
    },
    {
        "colo": "Default",
        "ip": "2606:4700:3034:ab84:2429:259c:e6c7:dad9",
        "latency": 11,
        "line": "CM",
        "loss": 0,
        "node": "CBUS",
        "speed": 507,
        "time": "2024-11-15 04:26:48"
    },
    {
        "colo": "Default",
        "ip": "2606:4700:3034:87cf:3425:6359:d3a8:6272",
        "latency": 11,
        "line": "CM",
        "loss": 0,
        "node": "CBUS",
        "speed": 505,
        "time": "2024-11-15 04:26:48"
    },
    {
        "colo": "Default",
        "ip": "2606:4700:3034:1a21:8bab:69de:3c8d:a38d",
        "latency": 11,
        "line": "CM",
        "loss": 0,
        "node": "CBUS",
        "speed": 498,
        "time": "2024-11-15 04:26:48"
    },
    {
        "colo": "Default",
        "ip": "2606:4700:83bd:cc62:5d2b:2f4:4aaa:a4e8",
        "latency": 20,
        "line": "CT",
        "loss": 0,
        "node": "WEBH",
        "speed": 310,
        "time": "2024-11-15 04:25:17"
    },
    {
        "colo": "Default",
        "ip": "2606:4700:300a:be9b:d19a:3d58:e83f:304c",
        "latency": 1,
        "line": "CT",
        "loss": 0,
        "node": "WEBH",
        "speed": 309,
        "time": "2024-11-15 04:25:18"
    },
    {
        "colo": "Default",
        "ip": "2606:4700:83bd:6adb:b0e4:8d6b:311b:f8d0",
        "latency": 20,
        "line": "CT",
        "loss": 0,
        "node": "WEBH",
        "speed": 308,
        "time": "2024-11-15 04:25:19"
    },
    {
        "colo": "Default",
        "ip": "2606:4700:83bd:2a9f:c158:f3a:e543:a7df",
        "latency": 20,
        "line": "CT",
        "loss": 0,
        "node": "WEBH",
        "speed": 307,
        "time": "2024-11-15 04:25:20"
    },
    {
        "colo": "Default",
        "ip": "2606:4700:83bd:c869:32e1:6352:c230:cb70",
        "latency": 26,
        "line": "CT",
        "loss": 0,
        "node": "WEBH",
        "speed": 307,
        "time": "2024-11-15 04:25:19"
    },
    {
        "colo": "Default",
        "ip": "2606:4700:3034:9c93:8606:f199:8992:3834",
        "latency": 11,
        "line": "CU",
        "loss": 0,
        "node": "CBUS",
        "speed": 538,
        "time": "2024-11-15 04:26:48"
    },
    {
        "colo": "Default",
        "ip": "2606:4700:3034:4fa9:2a43:355c:fadb:278d",
        "latency": 11,
        "line": "CU",
        "loss": 0,
        "node": "CBUS",
        "speed": 527,
        "time": "2024-11-15 04:26:48"
    },
    {
        "colo": "Default",
        "ip": "2606:4700:3034:ab84:2429:259c:e6c7:dad9",
        "latency": 11,
        "line": "CU",
        "loss": 0,
        "node": "CBUS",
        "speed": 507,
        "time": "2024-11-15 04:26:48"
    },
    {
        "colo": "Default",
        "ip": "2606:4700:3034:87cf:3425:6359:d3a8:6272",
        "latency": 11,
        "line": "CU",
        "loss": 0,
        "node": "CBUS",
        "speed": 505,
        "time": "2024-11-15 04:26:48"
    },
    {
        "colo": "Default",
        "ip": "2606:4700:3034:1a21:8bab:69de:3c8d:a38d",
        "latency": 11,
        "line": "CU",
        "loss": 0,
        "node": "CBUS",
        "speed": 498,
        "time": "2024-11-15 04:26:48"
    }
]