[
    {
        "colo": "Default",
        "ip": "2606:4700:9a9f:da7d:2b57:7f91:6a56:8fdb",
        "latency": 156,
        "line": "CM",
        "loss": 0,
        "node": "CBUS",
        "speed": 562,
        "time": "2024-10-30 23:54:29"
    },
    {
        "colo": "Default",
        "ip": "2606:4700:3016:358a:6f08:6f28:9e53:bf9f",
        "latency": 11,
        "line": "CM",
        "loss": 0,
        "node": "CBUS",
        "speed": 561,
        "time": "2024-10-30 23:54:29"
    },
    {
        "colo": "Default",
        "ip": "2606:4700:9a9f:c230:d52b:51ee:7c5d:32df",
        "latency": 150,
        "line": "CM",
        "loss": 0,
        "node": "CBUS",
        "speed": 511,
        "time": "2024-10-30 23:54:30"
    },
    {
        "colo": "Default",
        "ip": "2606:4700:9a9f:3402:1452:f50c:9cd5:8188",
        "latency": 159,
        "line": "CM",
        "loss": 0,
        "node": "CBUS",
        "speed": 495,
        "time": "2024-10-30 23:54:29"
    },
    {
        "colo": "Default",
        "ip": "2606:4700:3016:6d9b:7a37:2f63:92:5bf5",
        "latency": 11,
        "line": "CM",
        "loss": 0,
        "node": "CBUS",
        "speed": 377,
        "time": "2024-10-30 23:54:29"
    },
    {
        "colo": "Default",
        "ip": "2606:4700:964e:67c:e341:6b7e:95d1:2fd2",
        "latency": 20,
        "line": "CT",
        "loss": 0,
        "node": "WEBH",
        "speed": 310,
        "time": "2024-10-30 23:55:28"
    },
    {
        "colo": "Default",
        "ip": "2606:4700:9c6c:3a78:5532:7ccb:9200:2c67",
        "latency": 25,
        "line": "CT",
        "loss": 0,
        "node": "WEBH",
        "speed": 310,
        "time": "2024-10-30 23:55:27"
    },
    {
        "colo": "Default",
        "ip": "2606:4700:964e:7b3e:331c:3721:30a3:3aad",
        "latency": 20,
        "line": "CT",
        "loss": 0,
        "node": "WEBH",
        "speed": 309,
        "time": "2024-10-30 23:55:30"
    },
    {
        "colo": "Default",
        "ip": "2606:4700:9c6c:d97a:51c2:bcae:926c:81e5",
        "latency": 24,
        "line": "CT",
        "loss": 0,
        "node": "WEBH",
        "speed": 308,
        "time": "2024-10-30 23:55:29"
    },
    {
        "colo": "Default",
        "ip": "2606:4700:9c6c:4652:747d:8773:3c5c:69c7",
        "latency": 19,
        "line": "CT",
        "loss": 0,
        "node": "WEBH",
        "speed": 307,
        "time": "2024-10-30 23:55:28"
    },
    {
        "colo": "Default",
        "ip": "2606:4700:9a9f:da7d:2b57:7f91:6a56:8fdb",
        "latency": 156,
        "line": "CU",
        "loss": 0,
        "node": "CBUS",
        "speed": 562,
        "time": "2024-10-30 23:54:29"
    },
    {
        "colo": "Default",
        "ip": "2606:4700:3016:358a:6f08:6f28:9e53:bf9f",
        "latency": 11,
        "line": "CU",
        "loss": 0,
        "node": "CBUS",
        "speed": 561,
        "time": "2024-10-30 23:54:29"
    },
    {
        "colo": "Default",
        "ip": "2606:4700:9a9f:c230:d52b:51ee:7c5d:32df",
        "latency": 150,
        "line": "CU",
        "loss": 0,
        "node": "CBUS",
        "speed": 511,
        "time": "2024-10-30 23:54:30"
    },
    {
        "colo": "Default",
        "ip": "2606:4700:9a9f:3402:1452:f50c:9cd5:8188",
        "latency": 159,
        "line": "CU",
        "loss": 0,
        "node": "CBUS",
        "speed": 495,
        "time": "2024-10-30 23:54:29"
    },
    {
        "colo": "Default",
        "ip": "2606:4700:3016:6d9b:7a37:2f63:92:5bf5",
        "latency": 11,
        "line": "CU",
        "loss": 0,
        "node": "CBUS",
        "speed": 377,
        "time": "2024-10-30 23:54:29"
    }
]