[
    {
        "colo": "Default",
        "ip": "2606:4700:101:e1bc:41ca:6288:e372:5ee7",
        "latency": 1,
        "line": "CM",
        "loss": 0,
        "node": "WW_HK",
        "speed": 308,
        "time": "2024-11-10 16:26:40"
    },
    {
        "colo": "Default",
        "ip": "2606:4700:91ba:4b0c:edb:fe1e:79c3:7b32",
        "latency": 9,
        "line": "CM",
        "loss": 0,
        "node": "WW_HK",
        "speed": 308,
        "time": "2024-11-10 16:26:40"
    },
    {
        "colo": "Default",
        "ip": "2606:4700:91ba:9c2a:cdf9:cf4c:8597:da8e",
        "latency": 6,
        "line": "CM",
        "loss": 0,
        "node": "WW_HK",
        "speed": 308,
        "time": "2024-11-10 16:26:39"
    },
    {
        "colo": "Default",
        "ip": "2606:4700:101:c888:c769:530c:7576:5d2c",
        "latency": 2,
        "line": "CM",
        "loss": 0,
        "node": "WW_HK",
        "speed": 307,
        "time": "2024-11-10 16:26:39"
    },
    {
        "colo": "Default",
        "ip": "2606:4700:91ba:feb6:bdfb:1d30:9b55:1cb0",
        "latency": 1,
        "line": "CM",
        "loss": 0,
        "node": "WW_HK",
        "speed": 307,
        "time": "2024-11-10 16:26:38"
    },
    {
        "colo": "Default",
        "ip": "2606:4700:4401:dcb9:c79d:adcb:1be8:2327",
        "latency": 1,
        "line": "CT",
        "loss": 0,
        "node": "WEBH",
        "speed": 309,
        "time": "2024-11-10 16:25:22"
    },
    {
        "colo": "Default",
        "ip": "2606:4700:3008:edd2:4a4a:3558:bbe0:a424",
        "latency": 1,
        "line": "CT",
        "loss": 0,
        "node": "WEBH",
        "speed": 308,
        "time": "2024-11-10 16:25:23"
    },
    {
        "colo": "Default",
        "ip": "2606:4700:4401:655b:4895:3175:16b9:270",
        "latency": 1,
        "line": "CT",
        "loss": 0,
        "node": "WEBH",
        "speed": 307,
        "time": "2024-11-10 16:25:21"
    },
    {
        "colo": "Default",
        "ip": "2606:4700:4401:cb9f:d697:35dd:68e7:ebc8",
        "latency": 1,
        "line": "CT",
        "loss": 0,
        "node": "WEBH",
        "speed": 307,
        "time": "2024-11-10 16:25:23"
    },
    {
        "colo": "Default",
        "ip": "2606:4700:4401:4858:27e9:cd1d:bd21:5763",
        "latency": 1,
        "line": "CT",
        "loss": 0,
        "node": "WEBH",
        "speed": 307,
        "time": "2024-11-10 16:25:21"
    },
    {
        "colo": "Default",
        "ip": "2606:4700:101:e1bc:41ca:6288:e372:5ee7",
        "latency": 1,
        "line": "CU",
        "loss": 0,
        "node": "WW_HK",
        "speed": 308,
        "time": "2024-11-10 16:26:40"
    },
    {
        "colo": "Default",
        "ip": "2606:4700:91ba:4b0c:edb:fe1e:79c3:7b32",
        "latency": 9,
        "line": "CU",
        "loss": 0,
        "node": "WW_HK",
        "speed": 308,
        "time": "2024-11-10 16:26:40"
    },
    {
        "colo": "Default",
        "ip": "2606:4700:91ba:9c2a:cdf9:cf4c:8597:da8e",
        "latency": 6,
        "line": "CU",
        "loss": 0,
        "node": "WW_HK",
        "speed": 308,
        "time": "2024-11-10 16:26:39"
    },
    {
        "colo": "Default",
        "ip": "2606:4700:101:c888:c769:530c:7576:5d2c",
        "latency": 2,
        "line": "CU",
        "loss": 0,
        "node": "WW_HK",
        "speed": 307,
        "time": "2024-11-10 16:26:39"
    },
    {
        "colo": "Default",
        "ip": "2606:4700:91ba:feb6:bdfb:1d30:9b55:1cb0",
        "latency": 1,
        "line": "CU",
        "loss": 0,
        "node": "WW_HK",
        "speed": 307,
        "time": "2024-11-10 16:26:38"
    }
]