[
    {
        "colo": "Default",
        "ip": "2606:4700:8ddc:b480:20:d21b:1e1c:5833",
        "latency": 296,
        "line": "CM",
        "loss": 0,
        "node": "WW_HK",
        "speed": 309,
        "time": "2024-11-04 19:56:28"
    },
    {
        "colo": "Default",
        "ip": "2606:4700:8ddc:9cec:d28b:9d87:1452:2559",
        "latency": 296,
        "line": "CM",
        "loss": 0,
        "node": "WW_HK",
        "speed": 309,
        "time": "2024-11-04 19:56:27"
    },
    {
        "colo": "Default",
        "ip": "2606:4700:8ddc:ef58:5efb:cfff:b53c:8e24",
        "latency": 296,
        "line": "CM",
        "loss": 0,
        "node": "WW_HK",
        "speed": 307,
        "time": "2024-11-04 19:56:30"
    },
    {
        "colo": "Default",
        "ip": "2606:4700:8ddc:25aa:27ea:be2b:7558:913b",
        "latency": 296,
        "line": "CM",
        "loss": 0,
        "node": "WW_HK",
        "speed": 307,
        "time": "2024-11-04 19:56:29"
    },
    {
        "colo": "Default",
        "ip": "2606:4700:8ddc:e902:a822:675:aec1:9d32",
        "latency": 296,
        "line": "CM",
        "loss": 0,
        "node": "WW_HK",
        "speed": 307,
        "time": "2024-11-04 19:56:28"
    },
    {
        "colo": "Default",
        "ip": "2606:4700:964d:2897:5e5b:e031:91ac:e053",
        "latency": 24,
        "line": "CT",
        "loss": 0,
        "node": "WEBH",
        "speed": 309,
        "time": "2024-11-04 19:45:26"
    },
    {
        "colo": "Default",
        "ip": "2606:4700:964d:8b18:25a2:8229:4a68:ce67",
        "latency": 26,
        "line": "CT",
        "loss": 0,
        "node": "WEBH",
        "speed": 309,
        "time": "2024-11-04 19:45:24"
    },
    {
        "colo": "Default",
        "ip": "2606:4700:964d:ce4e:f7e:8b12:c611:e917",
        "latency": 23,
        "line": "CT",
        "loss": 0,
        "node": "WEBH",
        "speed": 308,
        "time": "2024-11-04 19:45:27"
    },
    {
        "colo": "Default",
        "ip": "2606:4700:964d:9c78:e2f4:84cf:6bac:6035",
        "latency": 20,
        "line": "CT",
        "loss": 0,
        "node": "WEBH",
        "speed": 308,
        "time": "2024-11-04 19:45:24"
    },
    {
        "colo": "Default",
        "ip": "2606:4700:964d:dc75:feea:8426:fe38:55a9",
        "latency": 25,
        "line": "CT",
        "loss": 0,
        "node": "WEBH",
        "speed": 307,
        "time": "2024-11-04 19:45:25"
    },
    {
        "colo": "Default",
        "ip": "2606:4700:8ddc:b480:20:d21b:1e1c:5833",
        "latency": 296,
        "line": "CU",
        "loss": 0,
        "node": "WW_HK",
        "speed": 309,
        "time": "2024-11-04 19:56:28"
    },
    {
        "colo": "Default",
        "ip": "2606:4700:8ddc:9cec:d28b:9d87:1452:2559",
        "latency": 296,
        "line": "CU",
        "loss": 0,
        "node": "WW_HK",
        "speed": 309,
        "time": "2024-11-04 19:56:27"
    },
    {
        "colo": "Default",
        "ip": "2606:4700:8ddc:ef58:5efb:cfff:b53c:8e24",
        "latency": 296,
        "line": "CU",
        "loss": 0,
        "node": "WW_HK",
        "speed": 307,
        "time": "2024-11-04 19:56:30"
    },
    {
        "colo": "Default",
        "ip": "2606:4700:8ddc:25aa:27ea:be2b:7558:913b",
        "latency": 296,
        "line": "CU",
        "loss": 0,
        "node": "WW_HK",
        "speed": 307,
        "time": "2024-11-04 19:56:29"
    },
    {
        "colo": "Default",
        "ip": "2606:4700:8ddc:e902:a822:675:aec1:9d32",
        "latency": 296,
        "line": "CU",
        "loss": 0,
        "node": "WW_HK",
        "speed": 307,
        "time": "2024-11-04 19:56:28"
    }
]