[
    {
        "colo": "Default",
        "ip": "2606:4700:91b1:a296:cb4d:ac91:8580:5a1e",
        "latency": 1,
        "line": "CM",
        "loss": 0,
        "node": "WW_HK",
        "speed": 310,
        "time": "2024-10-31 16:26:22"
    },
    {
        "colo": "Default",
        "ip": "2606:4700:91b1:ca8a:c074:44fa:2097:b016",
        "latency": 1,
        "line": "CM",
        "loss": 0,
        "node": "WW_HK",
        "speed": 308,
        "time": "2024-10-31 16:26:21"
    },
    {
        "colo": "Default",
        "ip": "2606:4700:440a:bbfe:40a7:6dc8:d5a:d6b5",
        "latency": 1,
        "line": "CM",
        "loss": 0,
        "node": "WW_HK",
        "speed": 308,
        "time": "2024-10-31 16:26:20"
    },
    {
        "colo": "Default",
        "ip": "2606:4700:440a:d8c7:5f3a:2e74:3fb4:9898",
        "latency": 0,
        "line": "CM",
        "loss": 0,
        "node": "WW_HK",
        "speed": 308,
        "time": "2024-10-31 16:26:19"
    },
    {
        "colo": "Default",
        "ip": "2606:4700:91b1:42ec:4fea:fef7:d244:42c3",
        "latency": 0,
        "line": "CM",
        "loss": 0,
        "node": "WW_HK",
        "speed": 307,
        "time": "2024-10-31 16:26:21"
    },
    {
        "colo": "Default",
        "ip": "2606:4700:964f:de6d:df65:688f:2a89:4fa4",
        "latency": 25,
        "line": "CT",
        "loss": 0,
        "node": "WEBH",
        "speed": 309,
        "time": "2024-10-31 16:25:28"
    },
    {
        "colo": "Default",
        "ip": "2606:4700:8ca9:6706:9400:c14c:cf80:357c",
        "latency": 23,
        "line": "CT",
        "loss": 0,
        "node": "WEBH",
        "speed": 309,
        "time": "2024-10-31 16:25:29"
    },
    {
        "colo": "Default",
        "ip": "2606:4700:8ca9:1a15:b8f1:d545:e00e:9f1d",
        "latency": 20,
        "line": "CT",
        "loss": 0,
        "node": "WEBH",
        "speed": 308,
        "time": "2024-10-31 16:25:27"
    },
    {
        "colo": "Default",
        "ip": "2606:4700:8ca9:f3e4:3a3a:d5f8:f927:32ce",
        "latency": 19,
        "line": "CT",
        "loss": 0,
        "node": "WEBH",
        "speed": 308,
        "time": "2024-10-31 16:25:26"
    },
    {
        "colo": "Default",
        "ip": "2606:4700:8ca9:ac9e:6c63:19a8:def1:2d82",
        "latency": 24,
        "line": "CT",
        "loss": 0,
        "node": "WEBH",
        "speed": 307,
        "time": "2024-10-31 16:25:28"
    },
    {
        "colo": "Default",
        "ip": "2606:4700:91b1:a296:cb4d:ac91:8580:5a1e",
        "latency": 1,
        "line": "CU",
        "loss": 0,
        "node": "WW_HK",
        "speed": 310,
        "time": "2024-10-31 16:26:22"
    },
    {
        "colo": "Default",
        "ip": "2606:4700:91b1:ca8a:c074:44fa:2097:b016",
        "latency": 1,
        "line": "CU",
        "loss": 0,
        "node": "WW_HK",
        "speed": 308,
        "time": "2024-10-31 16:26:21"
    },
    {
        "colo": "Default",
        "ip": "2606:4700:440a:bbfe:40a7:6dc8:d5a:d6b5",
        "latency": 1,
        "line": "CU",
        "loss": 0,
        "node": "WW_HK",
        "speed": 308,
        "time": "2024-10-31 16:26:20"
    },
    {
        "colo": "Default",
        "ip": "2606:4700:440a:d8c7:5f3a:2e74:3fb4:9898",
        "latency": 0,
        "line": "CU",
        "loss": 0,
        "node": "WW_HK",
        "speed": 308,
        "time": "2024-10-31 16:26:19"
    },
    {
        "colo": "Default",
        "ip": "2606:4700:91b1:42ec:4fea:fef7:d244:42c3",
        "latency": 0,
        "line": "CU",
        "loss": 0,
        "node": "WW_HK",
        "speed": 307,
        "time": "2024-10-31 16:26:21"
    }
]